romplas_hello/__init__.py
romplas_hello/core.py
romplas_hello-0.0.2.dist-info/METADATA
romplas_hello-0.0.2.dist-info/WHEEL
romplas_hello-0.0.2.dist-info/top_level.txt
romplas_hello-0.0.2.dist-info/RECORD
