Metadata-Version: 2.4
Name: romplas-hello
Version: 0.0.2
Summary: Pacote de exemplo da ROMPLAS
Author-email: Alberto MKt <marketing@romplas.com.br>
License: MIT
Requires-Python: >=3.9
